{"cameraMode":{"drawMode":0,"name":"Shaded","section":"Shading Mode"},"sceneLighting":true,"audioPlay":false,"sceneViewState":{"m_AlwaysRefresh":true,"showFog":true,"showSkybox":true,"showFlares":true,"showImageEffects":true,"showParticleSystems":true,"showVisualEffectGraphs":true,"m_FxEnabled":true},"in2DMode":false,"pivot":{"x":187.59230041503907,"y":3.803929328918457,"z":68.44794464111328},"rotation":{"x":0.10587657988071442,"y":0.8391929268836975,"z":-0.17650863528251649,"w":0.5033804178237915},"size":5.750485420227051,"orthographic":false}